Gray_to_Binary/gray_to_binary.v
// Gray to Binary Converter – 4-bit
module gray_to_binary (
    input wire [3:0] gray,
    output wire [3:0] binary
);

assign binary[3] = gray[3];                               // MSB is same
assign binary[2] = gray[3] ^ gray[2];
assign binary[1] = binary[2] ^ gray[1];
assign binary[0] = binary[1] ^ gray[0];

endmodule

Gray_to_Binary/gray_to_binary_tb.v
`timescale 1ns/1ps

module gray_to_binary_tb;

    reg [3:0] gray;
    wire [3:0] binary;

    gray_to_binary uut (
        .gray(gray),
        .binary(binary)
    );

    integer i;

    initial begin
        $dumpfile("gray_to_binary.vcd");
        $dumpvars(0, gray_to_binary_tb);

        // Test all 4-bit gray code values (0 to 15)
        for (i = 0; i < 16; i = i + 1) begin
            gray = i[3:0];
            #10;
        end

        $finish;
    end

endmodule

Gray_to_Binary/gray_to_binary.vcd
$date
	Fri Aug  8 12:04:50 2025
$end
$version
	Icarus Verilog
$end
$timescale
	1ps
$end
$scope module gray_to_binary_tb $end
$var wire 4 ! binary [3:0] $end
$var reg 4 " gray [3:0] $end
$var integer 32 # i [31:0] $end
$scope module uut $end
$var wire 4 $ gray [3:0] $end
$var wire 4 % binary [3:0] $end
$upscope $end
$upscope $end
$enddefinitions $end
$comment Show the parameter values. $end
$dumpall
$end
#0
$dumpvars
b0 %
b0 $
b0 #
b0 "
b0 !
$end
#10000
b1 !
b1 %
b1 "
b1 $
b1 #
#20000
b11 !
b11 %
b10 "
b10 $
b10 #
#30000
b10 !
b10 %
b11 "
b11 $
b11 #
#40000
b111 !
b111 %
b100 "
b100 $
b100 #
#50000
b110 !
b110 %
b101 "
b101 $
b101 #
#60000
b100 !
b100 %
b110 "
b110 $
b110 #
#70000
b101 !
b101 %
b111 "
b111 $
b111 #
#80000
b1111 !
b1111 %
b1000 "
b1000 $
b1000 #
#90000
b1110 !
b1110 %
b1001 "
b1001 $
b1001 #
#100000
b1100 !
b1100 %
b1010 "
b1010 $
b1010 #
#110000
b1101 !
b1101 %
b1011 "
b1011 $
b1011 #
#120000
b1000 !
b1000 %
b1100 "
b1100 $
b1100 #
#130000
b1001 !
b1001 %
b1101 "
b1101 $
b1101 #
#140000
b1011 !
b1011 %
b1110 "
b1110 $
b1110 #
#150000
b1010 !
b1010 %
b1111 "
b1111 $
b1111 #
#160000
b10000 #
