Mux 2_1/mux2to1.v
// 2:1 Multiplexer 
module mux2to1 (
    input a, b, sel,
    output y
);
    assign y = sel ? b : a;
endmodule

Mux 2_1/mux2to1_tb.v
// Testbench for 2:1 Multiplexer
`timescale 1ns/1ps

module mux2to1_tb;

    reg a, b, sel;
    wire y;

    // Instantiate the MUX
    mux2to1 uut (
        .a(a),
        .b(b),
        .sel(sel),
        .y(y)
    );

    initial begin
        // Dump file for GTKWave
        $dumpfile("mux2to1.vcd");
        $dumpvars(0, mux2to1_tb);

        // Apply test cases
        a = 0; b = 0; sel = 0; #10;
        a = 0; b = 1; sel = 0; #10;
        a = 1; b = 0; sel = 0; #10;
        a = 1; b = 1; sel = 0; #10;
        a = 0; b = 0; sel = 1; #10;
        a = 0; b = 1; sel = 1; #10;
        a = 1; b = 0; sel = 1; #10;
        a = 1; b = 1; sel = 1; #10;

        $finish;
    end

endmodule

Mux 2_1/mux2to1.vcd
$date
	Thu Aug  7 10:25:42 2025
$end
$version
	Icarus Verilog
$end
$timescale
	1ps
$end
$scope module mux2to1_tb $end
$var wire 1 ! y $end
$var reg 1 " a $end
$var reg 1 # b $end
$var reg 1 $ sel $end
$scope module uut $end
$var wire 1 " a $end
$var wire 1 # b $end
$var wire 1 $ sel $end
$var wire 1 ! y $end
$upscope $end
$upscope $end
$enddefinitions $end
$comment Show the parameter values. $end
$dumpall
$end
#0
$dumpvars
0$
0#
0"
0!
$end
#10000
1#
#20000
1!
0#
1"
#30000
1#
#40000
0!
1$
0#
0"
#50000
1!
1#
#60000
0!
0#
1"
#70000
1!
1#
