Memory_Controller/memory_controller.v
// memory_controller.v
// Clean variable names and simplified formatting

module memory_controller #(
    parameter DATA_WIDTH    = 8,
    parameter ADDR_WIDTH    = 16,
    parameter MEM_BASE_ADDR = 16'h1000,
    parameter MEM_ADDR_BITS = 11  // 2^11 = 2048 locations
) (
    // System Signals
    input                       clk,
    input                       reset_n,

    // CPU Interface
    input      [ADDR_WIDTH-1:0] cpu_addr,
    input      [DATA_WIDTH-1:0] cpu_write_data,
    input                       cpu_read_en,
    input                       cpu_write_en,
    output reg [DATA_WIDTH-1:0] cpu_read_data,
    output reg                  cpu_ready,

    // Memory Interface
    input      [DATA_WIDTH-1:0] mem_read_data,
    output     [MEM_ADDR_BITS-1:0] mem_addr,
    output     [DATA_WIDTH-1:0] mem_write_data,
    output reg                  mem_write_en,
    output reg                  mem_chip_en
);

    // State machine
    localparam [1:0] IDLE       = 2'b00,
                     WRITE_CYCLE = 2'b01,
                     READ_SETUP  = 2'b10,
                     READ_WAIT   = 2'b11;

    reg [1:0] state, next_state;

    // Address check
    wire addr_valid = (cpu_addr >= MEM_BASE_ADDR) && 
                      (cpu_addr < (MEM_BASE_ADDR + (1 << MEM_ADDR_BITS)));

    // Map CPU address to memory address
    assign mem_addr       = cpu_addr[MEM_ADDR_BITS-1:0];
    assign mem_write_data = cpu_write_data;

    // Next state and output logic
    always @(*) begin
        next_state   = state;
        cpu_ready    = 1'b0;
        mem_chip_en  = 1'b0;
        mem_write_en = 1'b0;

        case (state)
            IDLE: begin
                if (addr_valid) begin
                    if (cpu_write_en) begin
                        next_state = WRITE_CYCLE;
                    end else if (cpu_read_en) begin
                        next_state = READ_SETUP;
                    end
                end
            end

            WRITE_CYCLE: begin
                mem_chip_en  = 1'b1;
                mem_write_en = 1'b1;
                cpu_ready    = 1'b1;
                next_state   = IDLE;
            end

            READ_SETUP: begin
                mem_chip_en  = 1'b1;
                mem_write_en = 1'b0;
                next_state   = READ_WAIT;
            end

            READ_WAIT: begin
                mem_chip_en  = 1'b1;
                cpu_ready    = 1'b1;
                next_state   = IDLE;
            end
        endcase
    end

    // Sequential logic
    always @(posedge clk or negedge reset_n) begin
        if (!reset_n) begin
            state         <= IDLE;
            cpu_read_data <= 0;
        end else begin
            state <= next_state;
            if (state == READ_WAIT) begin
                cpu_read_data <= mem_read_data;
            end
        end
    end

endmodule

Memory_Controller/memory_controller_tb.v
// memory_controller_tb.v
// Clean variable names and formatting

`timescale 1ns / 1ps

module memory_controller_tb;

    // Parameters
    localparam DATA_WIDTH    = 8;
    localparam ADDR_WIDTH    = 16;
    localparam MEM_BASE_ADDR = 16'h1000;
    localparam MEM_ADDR_BITS = 11;
    localparam MEM_DEPTH     = 1 << MEM_ADDR_BITS;

    // Testbench signals
    reg                     clk;
    reg                     reset_n;
    integer                 i, fail_count = 0;
    reg  [ADDR_WIDTH-1:0]   rand_addr;
    reg  [DATA_WIDTH-1:0]   rand_data;

    // CPU side
    reg  [ADDR_WIDTH-1:0]   cpu_addr;
    reg  [DATA_WIDTH-1:0]   cpu_write_data;
    reg                     cpu_read_en;
    reg                     cpu_write_en;
    wire [DATA_WIDTH-1:0]   cpu_read_data;
    wire                    cpu_ready;

    // Memory side
    wire [DATA_WIDTH-1:0]   mem_read_data;
    wire [MEM_ADDR_BITS-1:0] mem_addr;
    wire [DATA_WIDTH-1:0]   mem_write_data;
    wire                    mem_write_en;
    wire                    mem_chip_en;

    // DUT
    memory_controller #(
        .DATA_WIDTH(DATA_WIDTH),
        .ADDR_WIDTH(ADDR_WIDTH),
        .MEM_BASE_ADDR(MEM_BASE_ADDR),
        .MEM_ADDR_BITS(MEM_ADDR_BITS)
    ) dut (
        .clk(clk),
        .reset_n(reset_n),
        .cpu_addr(cpu_addr),
        .cpu_write_data(cpu_write_data),
        .cpu_read_en(cpu_read_en),
        .cpu_write_en(cpu_write_en),
        .cpu_read_data(cpu_read_data),
        .cpu_ready(cpu_ready),
        .mem_read_data(mem_read_data),
        .mem_addr(mem_addr),
        .mem_write_data(mem_write_data),
        .mem_write_en(mem_write_en),
        .mem_chip_en(mem_chip_en)
    );

    // Simple synchronous RAM model
    reg [DATA_WIDTH-1:0] ram[0:MEM_DEPTH-1];
    always @(posedge clk) begin
        if (mem_chip_en && mem_write_en) begin
            ram[mem_addr] <= mem_write_data;
        end
    end
    assign mem_read_data = ram[mem_addr];

    // Clock generator
    always #5 clk = ~clk;

    // Write task
    task write_mem(input [ADDR_WIDTH-1:0] addr, input [DATA_WIDTH-1:0] data);
    begin
        @(posedge clk);
        cpu_addr       <= addr;
        cpu_write_data <= data;
        cpu_write_en   <= 1'b1;
        @(posedge clk);
        cpu_write_en   <= 1'b0;
        while (!cpu_ready) @(posedge clk);
        $display("[%t] WRITE: 0x%h -> 0x%h", $time, data, addr);
    end
    endtask

    // Read task
    task read_mem(input [ADDR_WIDTH-1:0] addr);
    begin
        @(posedge clk);
        cpu_addr     <= addr;
        cpu_read_en  <= 1'b1;
        @(posedge clk);
        cpu_read_en  <= 1'b0;
        while (!cpu_ready) @(posedge clk);
        $display("[%t] READ: 0x%h", $time, addr);
    end
    endtask

    // Main sequence
    initial begin
        $dumpfile("memory_controller.vcd");
        $dumpvars(0, memory_controller_tb);

        clk = 0;
        reset_n = 0;
        cpu_addr = 0;
        cpu_write_data = 0;
        cpu_read_en = 0;
        cpu_write_en = 0;

        #20 reset_n = 1;
        #20;

        for (i = 0; i < 8; i = i + 1) begin
            rand_addr = MEM_BASE_ADDR + {$random} % MEM_DEPTH;
            rand_data = {$random};

            write_mem(rand_addr, rand_data);
            read_mem(rand_addr);
            @(posedge clk);

            if (cpu_read_data == rand_data) begin
                $display("--> PASS: Data match 0x%h", cpu_read_data);
            end else begin
                $display("--> FAIL: Expected 0x%h, got 0x%h", rand_data, cpu_read_data);
                fail_count = fail_count + 1;
            end
            #50;
        end

        $display("\nFINAL SUMMARY:");
        if (fail_count == 0)
            $display("ALL TESTS PASSED");
        else
            $display("%0d TESTS FAILED", fail_count);

        $finish;
    end

endmodule

Memory_Controller/memory_controller.vcd
$date
	Tue Aug 12 18:17:13 2025
$end
$version
	Icarus Verilog
$end
$timescale
	1ps
$end
$scope module memory_controller_tb $end
$var wire 8 ! mem_read_data [7:0] $end
$var wire 1 " mem_write_en $end
$var wire 8 # mem_write_data [7:0] $end
$var wire 1 $ mem_chip_en $end
$var wire 11 % mem_addr [10:0] $end
$var wire 1 & cpu_ready $end
$var wire 8 ' cpu_read_data [7:0] $end
$var parameter 32 ( ADDR_WIDTH $end
$var parameter 32 ) DATA_WIDTH $end
$var parameter 32 * MEM_ADDR_BITS $end
$var parameter 16 + MEM_BASE_ADDR $end
$var parameter 43 , MEM_DEPTH $end
$var reg 1 - clk $end
$var reg 16 . cpu_addr [15:0] $end
$var reg 1 / cpu_read_en $end
$var reg 8 0 cpu_write_data [7:0] $end
$var reg 1 1 cpu_write_en $end
$var reg 16 2 rand_addr [15:0] $end
$var reg 8 3 rand_data [7:0] $end
$var reg 1 4 reset_n $end
$var integer 32 5 fail_count [31:0] $end
$var integer 32 6 i [31:0] $end
$scope module dut $end
$var wire 1 7 addr_valid $end
$var wire 1 - clk $end
$var wire 16 8 cpu_addr [15:0] $end
$var wire 1 / cpu_read_en $end
$var wire 8 9 cpu_write_data [7:0] $end
$var wire 1 1 cpu_write_en $end
$var wire 8 : mem_read_data [7:0] $end
$var wire 8 ; mem_write_data [7:0] $end
$var wire 1 4 reset_n $end
$var wire 11 < mem_addr [10:0] $end
$var parameter 32 = ADDR_WIDTH $end
$var parameter 32 > DATA_WIDTH $end
$var parameter 2 ? IDLE $end
$var parameter 32 @ MEM_ADDR_BITS $end
$var parameter 16 A MEM_BASE_ADDR $end
$var parameter 2 B READ_SETUP $end
$var parameter 2 C READ_WAIT $end
$var parameter 2 D WRITE_CYCLE $end
$var reg 8 E cpu_read_data [7:0] $end
$var reg 1 & cpu_ready $end
$var reg 1 $ mem_chip_en $end
$var reg 1 " mem_write_en $end
$var reg 2 F next_state [1:0] $end
$var reg 2 G state [1:0] $end
$upscope $end
$scope task read_mem $end
$var reg 16 H addr [15:0] $end
$upscope $end
$scope task write_mem $end
$var reg 16 I addr [15:0] $end
$var reg 8 J data [7:0] $end
$upscope $end
$upscope $end
$enddefinitions $end
$comment Show the parameter values. $end
$dumpall
b1 D
b11 C
b10 B
b1000000000000 A
b1011 @
b0 ?
b1000 >
b10000 =
b100000000000 ,
b1000000000000 +
b1011 *
b1000 )
b10000 (
$end
#0
$dumpvars
bx J
bx I
bx H
b0 G
b0 F
b0 E
b0 <
b0 ;
bx :
b0 9
b0 8
07
bx 6
b0 5
04
bx 3
bx 2
01
b0 0
0/
b0 .
0-
b0 '
0&
b0 %
0$
b0 #
0"
bx !
$end
#5000
1-
#10000
0-
#15000
1-
#20000
0-
14
#25000
1-
#30000
0-
#35000
1-
#40000
0-
b10000001 J
b1010100100100 I
b10000001 3
b1010100100100 2
b0 6
#45000
b1 F
17
b10100100100 %
b10100100100 <
11
b10000001 #
b10000001 ;
b10000001 0
b10000001 9
b1010100100100 .
b1010100100100 8
1-
#50000
0-
#55000
b0 F
1&
1"
1$
b1 G
01
1-
#60000
0-
#65000
0"
0$
0&
b0 G
b10000001 !
b10000001 :
b1010100100100 H
1-
#70000
0-
#75000
b10 F
1/
1-
#80000
0-
#85000
b11 F
1$
b10 G
0/
1-
#90000
0-
#95000
b0 F
1&
1$
b11 G
1-
#100000
0-
#105000
0$
0&
b10000001 '
b10000001 E
b0 G
1-
#110000
0-
#115000
1-
#120000
0-
#125000
1-
#130000
0-
#135000
1-
#140000
0-
#145000
1-
#150000
0-
#155000
1-
#160000
0-
#165000
b1 F
bx !
bx :
b11000001001 %
b11000001001 <
11
b1100011 #
b1100011 ;
b1100011 0
b1100011 9
b1011000001001 .
b1011000001001 8
1-
b1100011 J
b1011000001001 I
b1100011 3
b1011000001001 2
b1 6
#170000
0-
#175000
b0 F
1&
1"
1$
b1 G
01
1-
#180000
0-
#185000
0"
0$
0&
b0 G
b1100011 !
b1100011 :
b1011000001001 H
1-
#190000
0-
#195000
b10 F
1/
1-
#200000
0-
#205000
b11 F
1$
b10 G
0/
1-
#210000
0-
#215000
b0 F
1&
1$
b11 G
1-
#220000
0-
#225000
0$
0&
b1100011 '
b1100011 E
b0 G
1-
#230000
0-
#235000
1-
#240000
0-
#245000
1-
#250000
0-
#255000
1-
#260000
0-
#265000
1-
#270000
0-
#275000
1-
#280000
0-
#285000
b1 F
bx !
bx :
b1100001101 %
b1100001101 <
11
b10001101 #
b10001101 ;
b10001101 0
b10001101 9
b1001100001101 .
b1001100001101 8
1-
b10001101 J
b1001100001101 I
b10001101 3
b1001100001101 2
b10 6
#290000
0-
#295000
b0 F
1&
1"
1$
b1 G
01
1-
#300000
0-
#305000
0"
0$
0&
b0 G
b10001101 !
b10001101 :
b1001100001101 H
1-
#310000
0-
#315000
b10 F
1/
1-
#320000
0-
#325000
b11 F
1$
b10 G
0/
1-
#330000
0-
#335000
b0 F
1&
1$
b11 G
1-
#340000
0-
#345000
0$
0&
b10001101 '
b10001101 E
b0 G
1-
#350000
0-
#355000
1-
#360000
0-
#365000
1-
#370000
0-
#375000
1-
#380000
0-
#385000
1-
#390000
0-
#395000
1-
#400000
0-
#405000
b1 F
bx !
bx :
b10001100101 %
b10001100101 <
11
b10010 #
b10010 ;
b10010 0
b10010 9
b1010001100101 .
b1010001100101 8
1-
b10010 J
b1010001100101 I
b10010 3
b1010001100101 2
b11 6
#410000
0-
#415000
b0 F
1&
1"
1$
b1 G
01
1-
#420000
0-
#425000
0"
0$
0&
b0 G
b10010 !
b10010 :
b1010001100101 H
1-
#430000
0-
#435000
b10 F
1/
1-
#440000
0-
#445000
b11 F
1$
b10 G
0/
1-
#450000
0-
#455000
b0 F
1&
1$
b11 G
1-
#460000
0-
#465000
0$
0&
b10010 '
b10010 E
b0 G
1-
#470000
0-
#475000
1-
#480000
0-
#485000
1-
#490000
0-
#495000
1-
#500000
0-
#505000
1-
#510000
0-
#515000
1-
#520000
0-
#525000
b1 F
bx !
bx :
b1100000001 %
b1100000001 <
11
b1101 #
b1101 ;
b1101 0
b1101 9
b1001100000001 .
b1001100000001 8
1-
b1101 J
b1001100000001 I
b1101 3
b1001100000001 2
b100 6
#530000
0-
#535000
b0 F
1&
1"
1$
b1 G
01
1-
#540000
0-
#545000
0"
0$
0&
b0 G
b1101 !
b1101 :
b1001100000001 H
1-
#550000
0-
#555000
b10 F
1/
1-
#560000
0-
#565000
b11 F
1$
b10 G
0/
1-
#570000
0-
#575000
b0 F
1&
1$
b11 G
1-
#580000
0-
#585000
0$
0&
b1101 '
b1101 E
b0 G
1-
#590000
0-
#595000
1-
#600000
0-
#605000
1-
#610000
0-
#615000
1-
#620000
0-
#625000
1-
#630000
0-
#635000
1-
#640000
0-
#645000
b1 F
bx !
bx :
b101110110 %
b101110110 <
11
b111101 #
b111101 ;
b111101 0
b111101 9
b1000101110110 .
b1000101110110 8
1-
b111101 J
b1000101110110 I
b111101 3
b1000101110110 2
b101 6
#650000
0-
#655000
b0 F
1&
1"
1$
b1 G
01
1-
#660000
0-
#665000
0"
0$
0&
b0 G
b111101 !
b111101 :
b1000101110110 H
1-
#670000
0-
#675000
b10 F
1/
1-
#680000
0-
#685000
b11 F
1$
b10 G
0/
1-
#690000
0-
#695000
b0 F
1&
1$
b11 G
1-
#700000
0-
#705000
0$
0&
b111101 '
b111101 E
b0 G
1-
#710000
0-
#715000
1-
#720000
0-
#725000
1-
#730000
0-
#735000
1-
#740000
0-
#745000
1-
#750000
0-
#755000
1-
#760000
0-
#765000
b1 F
bx !
bx :
b11111101101 %
b11111101101 <
11
b10001100 #
b10001100 ;
b10001100 0
b10001100 9
b1011111101101 .
b1011111101101 8
1-
b10001100 J
b1011111101101 I
b10001100 3
b1011111101101 2
b110 6
#770000
0-
#775000
b0 F
1&
1"
1$
b1 G
01
1-
#780000
0-
#785000
0"
0$
0&
b0 G
b10001100 !
b10001100 :
b1011111101101 H
1-
#790000
0-
#795000
b10 F
1/
1-
#800000
0-
#805000
b11 F
1$
b10 G
0/
1-
#810000
0-
#815000
b0 F
1&
1$
b11 G
1-
#820000
0-
#825000
0$
0&
b10001100 '
b10001100 E
b0 G
1-
#830000
0-
#835000
1-
#840000
0-
#845000
1-
#850000
0-
#855000
1-
#860000
0-
#865000
1-
#870000
0-
#875000
1-
#880000
0-
#885000
b1 F
bx !
bx :
b111111001 %
b111111001 <
11
b11000110 #
b11000110 ;
b11000110 0
b11000110 9
b1000111111001 .
b1000111111001 8
1-
b11000110 J
b1000111111001 I
b11000110 3
b1000111111001 2
b111 6
#890000
0-
#895000
b0 F
1&
1"
1$
b1 G
01
1-
#900000
0-
#905000
0"
0$
0&
b0 G
b11000110 !
b11000110 :
b1000111111001 H
1-
#910000
0-
#915000
b10 F
1/
1-
#920000
0-
#925000
b11 F
1$
b10 G
0/
1-
#930000
0-
#935000
b0 F
1&
1$
b11 G
1-
#940000
0-
#945000
0$
0&
b11000110 '
b11000110 E
b0 G
1-
#950000
0-
#955000
1-
#960000
0-
#965000
1-
#970000
0-
#975000
1-
#980000
0-
#985000
1-
#990000
0-
#995000
1-
#1000000
0-
#1005000
1-
b1000 6
