Priority_encoder/priority_encoder_8to3.v
// 8:3 Priority Encoder
// Encodes the highest-priority active input

module priority_encoder_8to3 (
    input wire [7:0] in,
    output reg [2:0] out,
    output reg valid
);

    always @(*) begin
        valid = 1'b1;
        casex (in)
            8'b1xxxxxxx: out = 3'b111;
            8'b01xxxxxx: out = 3'b110;
            8'b001xxxxx: out = 3'b101;
            8'b0001xxxx: out = 3'b100;
            8'b00001xxx: out = 3'b011;
            8'b000001xx: out = 3'b010;
            8'b0000001x: out = 3'b001;
            8'b00000001: out = 3'b000;
            default: begin
                out = 3'b000;
                valid = 1'b0;
            end
        endcase
    end

endmodule

Priority_encoder/priority_encoder_8to3_tb.v
// Testbench for 8:3 Priority Encoder
`timescale 1ns/1ps

module priority_encoder_8to3_tb;

    reg [7:0] in;
    wire [2:0] out;
    wire valid;

    // Instantiate DUT
    priority_encoder_8to3 uut (
        .in(in),
        .out(out),
        .valid(valid)
    );

    initial begin
        $dumpfile("priority_encoder_8to3.vcd");
        $dumpvars(0, priority_encoder_8to3_tb);

        // Only one bit set at a time
        in = 8'b00000000; #10;
        in = 8'b00000001; #10;
        in = 8'b00000010; #10;
        in = 8'b00000100; #10;
        in = 8'b00001000; #10;
        in = 8'b00010000; #10;
        in = 8'b00100000; #10;
        in = 8'b01000000; #10;
        in = 8'b10000000; #10;

        // Multiple bits set (priority test)
        in = 8'b11001000; #10;
        in = 8'b00000011; #10;

        $finish;
    end

endmodule

Priority_encoder/priority_encoder_8to3.vcd
$date
	Fri Aug  8 16:01:28 2025
$end
$version
	Icarus Verilog
$end
$timescale
	1ps
$end
$scope module priority_encoder_8to3_tb $end
$var wire 1 ! valid $end
$var wire 3 " out [2:0] $end
$var reg 8 # in [7:0] $end
$scope module uut $end
$var wire 8 $ in [7:0] $end
$var reg 3 % out [2:0] $end
$var reg 1 ! valid $end
$upscope $end
$upscope $end
$enddefinitions $end
$comment Show the parameter values. $end
$dumpall
$end
#0
$dumpvars
b0 %
b0 $
b0 #
b0 "
0!
$end
#10000
1!
b1 #
b1 $
#20000
b1 "
b1 %
b10 #
b10 $
#30000
b10 "
b10 %
b100 #
b100 $
#40000
b11 "
b11 %
b1000 #
b1000 $
#50000
b100 "
b100 %
b10000 #
b10000 $
#60000
b101 "
b101 %
b100000 #
b100000 $
#70000
b110 "
b110 %
b1000000 #
b1000000 $
#80000
b111 "
b111 %
b10000000 #
b10000000 $
#90000
b11001000 #
b11001000 $
#100000
b1 "
b1 %
b11 #
b11 $
