D_Flip_flop/d_flip_flop.v
// D Flip-Flop (Positive Edge-Triggered)
module d_flip_flop (
    input wire clk,
    input wire d,
    output reg q
);
    always @(posedge clk) begin
        q <= d;
    end
endmodule

D_Flip_flop/d_flip_flop_tb.v
// Testbench for D Flip-Flop
`timescale 1ns/1ps

module d_flip_flop_tb;

    reg clk, d;
    wire q;

    // Instantiate DUT
    d_flip_flop uut (
        .clk(clk),
        .d(d),
        .q(q)
    );

    // Clock generator
    always #5 clk = ~clk;

    initial begin
        $dumpfile("d_flip_flop.vcd");
        $dumpvars(0, d_flip_flop_tb);

        clk = 0;
        d = 0;

        #12 d = 1;
        #10 d = 0;
        #10 d = 1;
        #10 d = 1;
        #10 d = 0;
        #10 $finish;
    end

endmodule

D_Flip_flop/d_flip_flop.vcd
$date
	Thu Aug  7 18:38:06 2025
$end
$version
	Icarus Verilog
$end
$timescale
	1ps
$end
$scope module d_flip_flop_tb $end
$var wire 1 ! q $end
$var reg 1 " clk $end
$var reg 1 # d $end
$scope module uut $end
$var wire 1 " clk $end
$var wire 1 # d $end
$var reg 1 ! q $end
$upscope $end
$upscope $end
$enddefinitions $end
$comment Show the parameter values. $end
$dumpall
$end
#0
$dumpvars
0#
0"
x!
$end
#5000
0!
1"
#10000
0"
#12000
1#
#15000
1!
1"
#20000
0"
#22000
0#
#25000
0!
1"
#30000
0"
#32000
1#
#35000
1!
1"
#40000
0"
#45000
1"
#50000
0"
#52000
0#
#55000
0!
1"
