Ring_Counter/ring_counter.v
// 4-bit Ring Counter
module ring_counter (
    input wire clk,
    input wire rst,
    output reg [3:0] q
);
    initial q = 4'b0001;

    always @(posedge clk or posedge rst) begin
        if (rst)
            q <= 4'b0001;  // Initial value
        else
            q <= {q[2:0], q[3]}; // Rotate left
    end
endmodule

Ring_Counter/ring_counter_tb.v
`timescale 1ns/1ps

module ring_counter_tb;

    reg clk, rst;
    wire [3:0] q;

    ring_counter uut (
        .clk(clk),
        .rst(rst),
        .q(q)
    );

    always #5 clk = ~clk;

    initial begin
        $dumpfile("ring_counter.vcd");
        $dumpvars(0, ring_counter_tb);

        clk = 0; rst = 1; #10;
        rst = 0;

        // Let it run for several cycles
        #100;
        $finish;
    end

endmodule

Ring_Counter/ring_counter.vcd
$date
	Thu Aug  7 19:09:59 2025
$end
$version
	Icarus Verilog
$end
$timescale
	1ps
$end
$scope module ring_counter_tb $end
$var wire 4 ! q [3:0] $end
$var reg 1 " clk $end
$var reg 1 # rst $end
$scope module uut $end
$var wire 1 " clk $end
$var wire 1 # rst $end
$var reg 4 $ q [3:0] $end
$upscope $end
$upscope $end
$enddefinitions $end
$comment Show the parameter values. $end
$dumpall
$end
#0
$dumpvars
b1 $
1#
0"
b1 !
$end
#5000
1"
#10000
0"
0#
#15000
b10 !
b10 $
1"
#20000
0"
#25000
b100 !
b100 $
1"
#30000
0"
#35000
b1000 !
b1000 $
1"
#40000
0"
#45000
b1 !
b1 $
1"
#50000
0"
#55000
b10 !
b10 $
1"
#60000
0"
#65000
b100 !
b100 $
1"
#70000
0"
#75000
b1000 !
b1000 $
1"
#80000
0"
#85000
b1 !
b1 $
1"
#90000
0"
#95000
b10 !
b10 $
1"
#100000
0"
#105000
b100 !
b100 $
1"
