8_bit_up_down_counter/updown_counter_8bit.v
// 8-bit Up/Down Counter - Synchronous
module updown_counter_8bit (
    input wire clk,
    input wire rst,
    input wire up_down,     // 1 for up, 0 for down
    output reg [7:0] count
);

    always @(posedge clk or posedge rst) begin
        if (rst)
            count <= 8'b0;
        else begin
            if (up_down)
                count <= count + 1;
            else
                count <= count - 1;
        end
    end

endmodule

8_bit_up_down_counter/updown_counter_8bit_tb.v
// Testbench for 8-bit Up/Down Counter
`timescale 1ns/1ps

module updown_counter_8bit_tb;

    reg clk, rst, up_down;
    wire [7:0] count;

    // Instantiate the DUT
    updown_counter_8bit uut (
        .clk(clk),
        .rst(rst),
        .up_down(up_down),
        .count(count)
    );

    // Clock generation
    always #5 clk = ~clk;

    initial begin
        $dumpfile("updown_counter_8bit.vcd");
        $dumpvars(0, updown_counter_8bit_tb);

        clk = 0;
        rst = 1;
        up_down = 1; // Start with up count
        #10;

        rst = 0;

        // Count up
        #50;

        // Switch to down
        up_down = 0;
        #50;

        // Reset
        rst = 1; #10;
        rst = 0; #10;

        $finish;
    end

endmodule

8_bit_up_down_counter/updown_counter_8bit.vcd
$date
	Thu Aug  7 18:23:00 2025
$end
$version
	Icarus Verilog
$end
$timescale
	1ps
$end
$scope module updown_counter_8bit_tb $end
$var wire 8 ! count [7:0] $end
$var reg 1 " clk $end
$var reg 1 # rst $end
$var reg 1 $ up_down $end
$scope module uut $end
$var wire 1 " clk $end
$var wire 1 # rst $end
$var wire 1 $ up_down $end
$var reg 8 % count [7:0] $end
$upscope $end
$upscope $end
$enddefinitions $end
$comment Show the parameter values. $end
$dumpall
$end
#0
$dumpvars
b0 %
1$
1#
0"
b0 !
$end
#5000
1"
#10000
0"
0#
#15000
b1 !
b1 %
1"
#20000
0"
#25000
b10 !
b10 %
1"
#30000
0"
#35000
b11 !
b11 %
1"
#40000
0"
#45000
b100 !
b100 %
1"
#50000
0"
#55000
b101 !
b101 %
1"
#60000
0"
0$
#65000
b100 !
b100 %
1"
#70000
0"
#75000
b11 !
b11 %
1"
#80000
0"
#85000
b10 !
b10 %
1"
#90000
0"
#95000
b1 !
b1 %
1"
#100000
0"
#105000
b0 !
b0 %
1"
#110000
0"
1#
#115000
1"
#120000
0"
0#
#125000
b11111111 !
b11111111 %
1"
