T_Flip_flop/t_flip_flop.v
module t_flip_flop (
    input wire clk,
    input wire t,
    output reg q
);
    initial q = 0; // This prevents X at start

    always @(posedge clk) begin
        if (t)
            q <= ~q;
    end
endmodule

T_Flip_flop/t_flip_flop_tb.v
// Testbench for T Flip-Flop
`timescale 1ns/1ps

module t_flip_flop_tb;

    reg clk, t;
    wire q;

    // Instantiate DUT
    t_flip_flop uut (
        .clk(clk),
        .t(t),
        .q(q)
    );

    // Clock generation
    always #5 clk = ~clk;

    initial begin
        $dumpfile("t_flip_flop.vcd");
        $dumpvars(0, t_flip_flop_tb);

        clk = 0;
        t = 0;

        #10 t = 1;
        #10 t = 1;
        #10 t = 0;
        #10 t = 1;
        #10 t = 0;
        #10 $finish;
    end

endmodule

T_Flip_flop/t_flip_flop.vcd
$date
	Thu Aug  7 18:52:09 2025
$end
$version
	Icarus Verilog
$end
$timescale
	1ps
$end
$scope module t_flip_flop_tb $end
$var wire 1 ! q $end
$var reg 1 " clk $end
$var reg 1 # t $end
$scope module uut $end
$var wire 1 " clk $end
$var wire 1 # t $end
$var reg 1 ! q $end
$upscope $end
$upscope $end
$enddefinitions $end
$comment Show the parameter values. $end
$dumpall
$end
#0
$dumpvars
0#
0"
0!
$end
#5000
1"
#10000
0"
1#
#15000
1!
1"
#20000
0"
#25000
0!
1"
#30000
0"
0#
#35000
1"
#40000
0"
1#
#45000
1!
1"
#50000
0"
0#
