JK_Flip_flop/jk_flip_flop.v
// JK Flip-Flop (Positive Edge-Triggered)
module jk_flip_flop (
    input wire clk,
    input wire j,
    input wire k,
    output reg q
);
    initial q = 0;

    always @(posedge clk) begin
        case ({j, k})
            2'b00: q <= q;         // No change
            2'b01: q <= 0;         // Reset
            2'b10: q <= 1;         // Set
            2'b11: q <= ~q;        // Toggle
        endcase
    end
endmodule

JK_Flip_flop/jk_flip_flop_tb.v
// Testbench for JK Flip-Flop
`timescale 1ns/1ps

module jk_flip_flop_tb;

    reg clk, j, k;
    wire q;

    jk_flip_flop uut (
        .clk(clk),
        .j(j),
        .k(k),
        .q(q)
    );

    // Clock generation
    always #5 clk = ~clk;

    initial begin
        $dumpfile("jk_flip_flop.vcd");
        $dumpvars(0, jk_flip_flop_tb);

        clk = 0; j = 0; k = 0;

        // Test all input combinations
        #10 j = 0; k = 0;  // No change
        #10 j = 1; k = 0;  // Set
        #10 j = 0; k = 1;  // Reset
        #10 j = 1; k = 1;  // Toggle
        #10 j = 1; k = 1;  // Toggle again
        #10 j = 0; k = 0;  // No change
        #10 $finish;
    end

endmodule

JK_Flip_flop/jk_flip_flop.vcd
$date
	Thu Aug  7 18:57:45 2025
$end
$version
	Icarus Verilog
$end
$timescale
	1ps
$end
$scope module jk_flip_flop_tb $end
$var wire 1 ! q $end
$var reg 1 " clk $end
$var reg 1 # j $end
$var reg 1 $ k $end
$scope module uut $end
$var wire 1 " clk $end
$var wire 1 # j $end
$var wire 1 $ k $end
$var reg 1 ! q $end
$upscope $end
$upscope $end
$enddefinitions $end
$comment Show the parameter values. $end
$dumpall
$end
#0
$dumpvars
0$
0#
0"
0!
$end
#5000
1"
#10000
0"
#15000
1"
#20000
0"
1#
#25000
1!
1"
#30000
0"
1$
0#
#35000
0!
1"
#40000
0"
1#
#45000
1!
1"
#50000
0"
#55000
0!
1"
#60000
0"
0$
0#
