Traffic_light_controller/traffic_light_controller.v
// Traffic Light Controller using FSM (3 states)
module traffic_light_controller (
    input wire clk,
    input wire rst,
    output reg [2:0] light
);

// Encoding lights: [2]=Red, [1]=Yellow, [0]=Green
// State encoding
parameter RED = 2'b00,
          GREEN = 2'b01,
          YELLOW = 2'b10;

reg [1:0] state, next_state;

// Counter for timing
reg [3:0] timer;

always @(posedge clk or posedge rst) begin
    if (rst) begin
        state <= RED;
        timer <= 0;
    end else begin
        if (state != next_state)
        timer <= 0;
        else
        timer <= timer + 1;
    state <= next_state;
    end
end

// Next state logic based on timer
always @(*) begin
    case (state)
        RED:    next_state = (timer == 4'd5) ? GREEN  : RED;
        GREEN:  next_state = (timer == 4'd5) ? YELLOW : GREEN;
        YELLOW: next_state = (timer == 4'd2) ? RED    : YELLOW;
        default: next_state = RED;
    endcase
end

// Output logic
always @(*) begin
    case (state)
        RED:    light = 3'b100; // Red ON
        GREEN:  light = 3'b001; // Green ON
        YELLOW: light = 3'b010; // Yellow ON
        default: light = 3'b000;
    endcase
end

endmodule

Traffic_light_controller/traffic_light_controller_tb.v
`timescale 1ns/1ps

module traffic_light_controller_tb;

    reg clk, rst;
    wire [2:0] light;

    traffic_light_controller uut (
        .clk(clk),
        .rst(rst),
        .light(light)
    );

    // Clock generation
    always #5 clk = ~clk;

    initial begin
        $dumpfile("traffic_light_controller.vcd");
        $dumpvars(0, traffic_light_controller_tb);

        clk = 0;
        rst = 1; #10;
        rst = 0;

        // Run simulation for 200 time units
        #300;
        $finish;
    end

endmodule

Traffic_light_controller/traffic_light_controller.vcd
$date
	Fri Aug  8 10:34:46 2025
$end
$version
	Icarus Verilog
$end
$timescale
	1ps
$end
$scope module traffic_light_controller_tb $end
$var wire 3 ! light [2:0] $end
$var reg 1 " clk $end
$var reg 1 # rst $end
$scope module uut $end
$var wire 1 " clk $end
$var wire 1 # rst $end
$var parameter 2 $ GREEN $end
$var parameter 2 % RED $end
$var parameter 2 & YELLOW $end
$var reg 3 ' light [2:0] $end
$var reg 2 ( next_state [1:0] $end
$var reg 2 ) state [1:0] $end
$var reg 4 * timer [3:0] $end
$upscope $end
$upscope $end
$enddefinitions $end
$comment Show the parameter values. $end
$dumpall
b10 &
b0 %
b1 $
$end
#0
$dumpvars
b0 *
b0 )
b0 (
b100 '
1#
0"
b100 !
$end
#5000
1"
#10000
0"
0#
#15000
b1 *
1"
#20000
0"
#25000
b10 *
1"
#30000
0"
#35000
b11 *
1"
#40000
0"
#45000
b100 *
1"
#50000
0"
#55000
b1 (
b101 *
1"
#60000
0"
#65000
b1 !
b1 '
b1 )
b0 *
1"
#70000
0"
#75000
b1 *
1"
#80000
0"
#85000
b10 *
1"
#90000
0"
#95000
b11 *
1"
#100000
0"
#105000
b100 *
1"
#110000
0"
#115000
b10 (
b101 *
1"
#120000
0"
#125000
b10 !
b10 '
b10 )
b0 *
1"
#130000
0"
#135000
b1 *
1"
#140000
0"
#145000
b0 (
b10 *
1"
#150000
0"
#155000
b100 !
b100 '
b0 )
b0 *
1"
#160000
0"
#165000
b1 *
1"
#170000
0"
#175000
b10 *
1"
#180000
0"
#185000
b11 *
1"
#190000
0"
#195000
b100 *
1"
#200000
0"
#205000
b1 (
b101 *
1"
#210000
0"
#215000
b1 !
b1 '
b1 )
b0 *
1"
#220000
0"
#225000
b1 *
1"
#230000
0"
#235000
b10 *
1"
#240000
0"
#245000
b11 *
1"
#250000
0"
#255000
b100 *
1"
#260000
0"
#265000
b10 (
b101 *
1"
#270000
0"
#275000
b10 !
b10 '
b10 )
b0 *
1"
#280000
0"
#285000
b1 *
1"
#290000
0"
#295000
b0 (
b10 *
1"
#300000
0"
#305000
b100 !
b100 '
b0 )
b0 *
1"
