SR_Flip_flop/sr_flip_flop.v
// SR Flip-Flop (Positive Edge-Triggered)
module sr_flip_flop (
    input wire clk,
    input wire s,    // Set
    input wire r,    // Reset
    output reg q
);
    initial q = 0;

    always @(posedge clk) begin
        case ({s, r})
            2'b00: q <= q;       // No change
            2'b01: q <= 0;       // Reset
            2'b10: q <= 1;       // Set
            2'b11: q <= 1'bx;    // Invalid (both set and reset)
        endcase
    end
endmodule

SR_Flip_flop/sr_flip_flop_tb.v
// Testbench for SR Flip-Flop
`timescale 1ns/1ps

module sr_flip_flop_tb;

    reg clk, s, r;
    wire q;

    sr_flip_flop uut (
        .clk(clk),
        .s(s),
        .r(r),
        .q(q)
    );

    always #5 clk = ~clk;

    initial begin
        $dumpfile("sr_flip_flop.vcd");
        $dumpvars(0, sr_flip_flop_tb);

        clk = 0; s = 0; r = 0;

        // Test each case
        #10 s = 0; r = 0; // Hold
        #10 s = 1; r = 0; // Set
        #10 s = 0; r = 1; // Reset
        #10 s = 1; r = 1; // Invalid
        #10 s = 0; r = 0; // Hold
        #10 $finish;
    end

endmodule

SR_Flip_flop/sr_flip_flop.vcd
$date
	Thu Aug  7 19:02:25 2025
$end
$version
	Icarus Verilog
$end
$timescale
	1ps
$end
$scope module sr_flip_flop_tb $end
$var wire 1 ! q $end
$var reg 1 " clk $end
$var reg 1 # r $end
$var reg 1 $ s $end
$scope module uut $end
$var wire 1 " clk $end
$var wire 1 # r $end
$var wire 1 $ s $end
$var reg 1 ! q $end
$upscope $end
$upscope $end
$enddefinitions $end
$comment Show the parameter values. $end
$dumpall
$end
#0
$dumpvars
0$
0#
0"
0!
$end
#5000
1"
#10000
0"
#15000
1"
#20000
0"
1$
#25000
1!
1"
#30000
0"
1#
0$
#35000
0!
1"
#40000
0"
1$
#45000
x!
1"
#50000
0"
0#
0$
