Sign_Extender/sign_extender.v
// Sign Extender – 4-bit to 8-bit
module sign_extender (
    input wire [3:0] in,
    output wire [7:0] out
);

// Replicate the MSB (sign bit) 4 times and concatenate
assign out = {{4{in[3]}}, in};

endmodule

Sign_Extender/sign_extender_tb.v
`timescale 1ns/1ps

module sign_extender_tb;

    reg  [3:0] in;
    wire [7:0] out;

    sign_extender uut (
        .in(in),
        .out(out)
    );

    integer i;

    initial begin
        $dumpfile("sign_extender.vcd");
        $dumpvars(0, sign_extender_tb);

        // Loop through all 4-bit values
        for (i = 0; i < 16; i = i + 1) begin
            in = i[3:0];
            #10;
        end

        $finish;
    end

endmodule

Sign_Extender/sign_extender.vcd
$date
	Fri Aug  8 13:37:54 2025
$end
$version
	Icarus Verilog
$end
$timescale
	1ps
$end
$scope module sign_extender_tb $end
$var wire 8 ! out [7:0] $end
$var reg 4 " in [3:0] $end
$var integer 32 # i [31:0] $end
$scope module uut $end
$var wire 4 $ in [3:0] $end
$var wire 8 % out [7:0] $end
$upscope $end
$upscope $end
$enddefinitions $end
$comment Show the parameter values. $end
$dumpall
$end
#0
$dumpvars
b0 %
b0 $
b0 #
b0 "
b0 !
$end
#10000
b1 !
b1 %
b1 "
b1 $
b1 #
#20000
b10 !
b10 %
b10 "
b10 $
b10 #
#30000
b11 !
b11 %
b11 "
b11 $
b11 #
#40000
b100 !
b100 %
b100 "
b100 $
b100 #
#50000
b101 !
b101 %
b101 "
b101 $
b101 #
#60000
b110 !
b110 %
b110 "
b110 $
b110 #
#70000
b111 !
b111 %
b111 "
b111 $
b111 #
#80000
b11111000 !
b11111000 %
b1000 "
b1000 $
b1000 #
#90000
b11111001 !
b11111001 %
b1001 "
b1001 $
b1001 #
#100000
b11111010 !
b11111010 %
b1010 "
b1010 $
b1010 #
#110000
b11111011 !
b11111011 %
b1011 "
b1011 $
b1011 #
#120000
b11111100 !
b11111100 %
b1100 "
b1100 $
b1100 #
#130000
b11111101 !
b11111101 %
b1101 "
b1101 $
b1101 #
#140000
b11111110 !
b11111110 %
b1110 "
b1110 $
b1110 #
#150000
b11111111 !
b11111111 %
b1111 "
b1111 $
b1111 #
#160000
b10000 #
