Pulse_Generator/pulse_generator.v
// Pulse Generator – One-shot pulse on trigger
module pulse_generator (
    input wire clk,
    input wire rst,
    input wire trigger,
    output reg pulse
);

    reg trigger_d;

    always @(posedge clk or posedge rst) begin
        if (rst) begin
            trigger_d <= 0;
            pulse <= 0;
        end else begin
            trigger_d <= trigger;
            pulse <= trigger & ~trigger_d; // rising edge detector
        end
    end

endmodule

Pulse_Generator/pulse_generator_tb.v
`timescale 1ns/1ps

module pulse_generator_tb;

    reg clk, rst, trigger;
    wire pulse;

    pulse_generator uut (
        .clk(clk),
        .rst(rst),
        .trigger(trigger),
        .pulse(pulse)
    );

    // Clock generation (10 ns period)
    always #5 clk = ~clk;

    initial begin
        $dumpfile("pulse_generator.vcd");
        $dumpvars(0, pulse_generator_tb);

        clk = 0; rst = 1; trigger = 0; #10;
        rst = 0;

        // Apply trigger pulses
        #10 trigger = 1; #10 trigger = 1; #10 trigger = 0;
        #20 trigger = 1; #10 trigger = 0;
        #20 trigger = 1; #10 trigger = 0;

        #20 $finish;
    end

endmodule

Pulse_Generator/pulse_generator.vcd
$date
	Thu Aug  7 23:21:06 2025
$end
$version
	Icarus Verilog
$end
$timescale
	1ps
$end
$scope module pulse_generator_tb $end
$var wire 1 ! pulse $end
$var reg 1 " clk $end
$var reg 1 # rst $end
$var reg 1 $ trigger $end
$scope module uut $end
$var wire 1 " clk $end
$var wire 1 # rst $end
$var wire 1 $ trigger $end
$var reg 1 ! pulse $end
$var reg 1 % trigger_d $end
$upscope $end
$upscope $end
$enddefinitions $end
$comment Show the parameter values. $end
$dumpall
$end
#0
$dumpvars
0%
0$
1#
0"
0!
$end
#5000
1"
#10000
0"
0#
#15000
1"
#20000
0"
1$
#25000
1!
1%
1"
#30000
0"
#35000
0!
1"
#40000
0"
0$
#45000
0%
1"
#50000
0"
#55000
1"
#60000
0"
1$
#65000
1!
1%
1"
#70000
0"
0$
#75000
0!
0%
1"
#80000
0"
#85000
1"
#90000
0"
1$
#95000
1!
1%
1"
#100000
0"
0$
#105000
0!
0%
1"
