Universal_shift_register/universal_shift_register.v
// Universal 4-bit Shift Register (SISO, SIPO, PISO, PIPO)

module universal_shift_register (
    input wire clk,
    input wire rst,
    input wire [1:0] mode,      // 00: Hold, 01: Shift Left, 10: Load Parallel, 11: Shift Right
    input wire s_in,            // Serial Input
    input wire [3:0] p_in,      // Parallel Input
    output wire s_out,          // Serial Output (MSB)
    output wire [3:0] p_out     // Parallel Output
);

    reg [3:0] shift_reg;

    always @(posedge clk or posedge rst) begin
        if (rst)
            shift_reg <= 4'b0000;
        else begin
            case (mode)
                2'b00: shift_reg <= shift_reg;                          // Hold
                2'b01: shift_reg <= {shift_reg[2:0], s_in};            // Shift Left (SISO/SIPO)
                2'b10: shift_reg <= p_in;                               // Load Parallel (PIPO)
                2'b11: shift_reg <= {s_in, shift_reg[3:1]};            // Shift Right (PISO)
            endcase
        end
    end

    assign s_out = shift_reg[3];  // Serial Output (MSB)
    assign p_out = shift_reg;     // Parallel Output

endmodule

Universal_shift_register/universal_shift_register_tb.v
// Testbench for Universal 4-bit Shift Register
`timescale 1ns/1ps

module universal_shift_register_tb;

    reg clk;
    reg rst;
    reg [1:0] mode;
    reg s_in;
    reg [3:0] p_in;
    wire s_out;
    wire [3:0] p_out;

    // Instantiate DUT
    universal_shift_register uut (
        .clk(clk),
        .rst(rst),
        .mode(mode),
        .s_in(s_in),
        .p_in(p_in),
        .s_out(s_out),
        .p_out(p_out)
    );

    // Clock generation
    always #5 clk = ~clk;

    initial begin
        $dumpfile("universal_shift_register.vcd");
        $dumpvars(0, universal_shift_register_tb);

        clk = 0; rst = 1; mode = 2'b00; s_in = 0; p_in = 4'b0000;
        #10;

        rst = 0;

        // Load parallel (PIPO)
        mode = 2'b10; p_in = 4'b1101; #10;

        // Hold
        mode = 2'b00; #10;

        // Shift left (SISO/SIPO)
        mode = 2'b01; s_in = 1; #10;
        s_in = 0; #10;

        // Shift right (PISO)
        mode = 2'b11; s_in = 1; #10;
        s_in = 1; #10;

        $finish;
    end

endmodule

Universal_shift_register/universal_shift_register.vcd
$date
	Fri Aug  8 14:12:06 2025
$end
$version
	Icarus Verilog
$end
$timescale
	1ps
$end
$scope module universal_shift_register_tb $end
$var wire 1 ! s_out $end
$var wire 4 " p_out [3:0] $end
$var reg 1 # clk $end
$var reg 2 $ mode [1:0] $end
$var reg 4 % p_in [3:0] $end
$var reg 1 & rst $end
$var reg 1 ' s_in $end
$scope module uut $end
$var wire 1 # clk $end
$var wire 2 ( mode [1:0] $end
$var wire 4 ) p_in [3:0] $end
$var wire 4 * p_out [3:0] $end
$var wire 1 & rst $end
$var wire 1 ' s_in $end
$var wire 1 ! s_out $end
$var reg 4 + shift_reg [3:0] $end
$upscope $end
$upscope $end
$enddefinitions $end
$comment Show the parameter values. $end
$dumpall
$end
#0
$dumpvars
b0 +
b0 *
b0 )
b0 (
0'
1&
b0 %
b0 $
0#
b0 "
0!
$end
#5000
1#
#10000
0#
b1101 %
b1101 )
b10 $
b10 (
0&
#15000
1!
b1101 "
b1101 *
b1101 +
1#
#20000
0#
b0 $
b0 (
#25000
1#
#30000
0#
1'
b1 $
b1 (
#35000
b1011 "
b1011 *
b1011 +
1#
#40000
0#
0'
#45000
0!
b110 "
b110 *
b110 +
1#
#50000
0#
1'
b11 $
b11 (
#55000
1!
b1011 "
b1011 *
b1011 +
1#
#60000
0#
#65000
b1101 "
b1101 *
b1101 +
1#
