Full_Adder/full_adder.v
// Full Adder
module full_adder (
    input wire a,
    input wire b,
    input wire cin,
    output wire sum,
    output wire cout
);
    assign sum = a ^ b ^ cin;
    assign cout = (a & b) | (b & cin) | (a & cin);
endmodule

Full_Adder/full_adder_tb.v
// Testbench for Full Adder
`timescale 1ns/1ps

module full_adder_tb;

    reg a, b, cin;
    wire sum, cout;

    // Instantiate the DUT
    full_adder uut (
        .a(a),
        .b(b),
        .cin(cin),
        .sum(sum),
        .cout(cout)
    );

    initial begin
        $dumpfile("full_adder.vcd");
        $dumpvars(0, full_adder_tb);

        // Test all combinations of a, b, cin
        a = 0; b = 0; cin = 0; #10;
        a = 0; b = 0; cin = 1; #10;
        a = 0; b = 1; cin = 0; #10;
        a = 0; b = 1; cin = 1; #10;
        a = 1; b = 0; cin = 0; #10;
        a = 1; b = 0; cin = 1; #10;
        a = 1; b = 1; cin = 0; #10;
        a = 1; b = 1; cin = 1; #10;

        $finish;
    end

endmodule

Full_Adder/full_adder.vcd
$date
	Thu Aug  7 17:37:18 2025
$end
$version
	Icarus Verilog
$end
$timescale
	1ps
$end
$scope module full_adder_tb $end
$var wire 1 ! sum $end
$var wire 1 " cout $end
$var reg 1 # a $end
$var reg 1 $ b $end
$var reg 1 % cin $end
$scope module uut $end
$var wire 1 # a $end
$var wire 1 $ b $end
$var wire 1 % cin $end
$var wire 1 " cout $end
$var wire 1 ! sum $end
$upscope $end
$upscope $end
$enddefinitions $end
$comment Show the parameter values. $end
$dumpall
$end
#0
$dumpvars
0%
0$
0#
0"
0!
$end
#10000
1!
1%
#20000
0%
1$
#30000
1"
0!
1%
#40000
0"
1!
0%
0$
1#
#50000
1"
0!
1%
#60000
0%
1$
#70000
1!
1%
