Booth_Multiplier/booth_multiplier_fsm.v
module booth_multiplier_fsm(clk,rst,start,X,Y,valid,Z);

input clk;
input rst;
input start;
input signed [3:0]X,Y;
output signed [7:0]Z;
output valid;

reg signed [7:0] Z,next_Z,Z_temp;
reg next_state, pres_state;
reg [1:0] temp,next_temp;
reg [1:0] count,next_count;
reg valid, next_valid;

parameter IDLE = 1'b0;
parameter START = 1'b1;

always @ (posedge clk or negedge rst)
begin
if(!rst)
begin
  Z          <= 8'd0;
  valid      <= 1'b0;
  pres_state <= 1'b0;
  temp       <= 2'd0;
  count      <= 2'd0;
end
else
begin
  Z          <= next_Z;
  valid      <= next_valid;
  pres_state <= next_state;
  temp       <= next_temp;
  count      <= next_count;
end
end

always @ (*)
begin 
case(pres_state)
IDLE:
begin
next_count = 2'b0;
next_valid = 1'b0;
if(start)
begin
    next_state = START;
    next_temp  = {X[0],1'b0};
    next_Z     = {4'd0,X};
end
else
begin
    next_state = pres_state;
    next_temp  = 2'd0;
    next_Z     = 8'd0;
end
end

START:
begin
    case(temp)
    2'b10:   Z_temp = {Z[7:4]-Y,Z[3:0]};
    2'b01:   Z_temp = {Z[7:4]+Y,Z[3:0]};
    default: Z_temp = {Z[7:4],Z[3:0]};
    endcase
next_temp  = {X[count+1],X[count]};
next_count = count + 1'b1;
next_Z     = Z_temp >>> 1;
next_valid = (&count) ? 1'b1 : 1'b0; 
next_state = (&count) ? IDLE : pres_state;  
end
endcase
end
endmodule

Booth_Multiplier/booth_multiplier_fsm_tb.v
// booth_multiplier_fsm_tb.v
`timescale 1ns / 1ps

module booth_multiplier_fsm_tb();

    reg clk;
    reg rst;
    reg start;
    reg signed [3:0] X, Y;
    wire signed [7:0] Z;
    wire valid;

    // Instantiate the DUT
    booth_multiplier_fsm uut (
        .clk(clk),
        .rst(rst),
        .start(start),
        .X(X),
        .Y(Y),
        .Z(Z),
        .valid(valid)
    );

    // Clock generation (period 10ns)
    initial clk = 0;
    always #5 clk = ~clk;

    initial begin
        $dumpfile("booth_multiplier_fsm.vcd");
        $dumpvars(0, booth_multiplier_fsm_tb);

        // Reset
        rst = 0; start = 0; X = 0; Y = 0;
        #15;
        rst = 1;
        #10;

        // Test 1: 3 * 4 = 12
        X = 4; Y = 3;
        start_pulse();
        wait(valid == 1);
        #10;
        $display("Test 1: %d * %d = %d (expected %d)", X, Y, Z, X*Y);

        // Test 2: -5 * 2 = -10
        X = -5; Y = 2;
        start_pulse();
        wait(valid == 1);
        #10;
        $display("Test 2: %d * %d = %d (expected %d)", X, Y, Z, X*Y);

        // Test 3: -3 * -3 = 9
        X = -3; Y = -3;
        start_pulse();
        wait(valid == 1);
        #10;
        $display("Test 3: %d * %d = %d (expected %d)", X, Y, Z, X*Y);

        // Test 4: 7 * -4 = -28
        X = 7; Y = -4;
        start_pulse();
        wait(valid == 1);
        #10;
        $display("Test 4: %d * %d = %d (expected %d)", X, Y, Z, X*Y);

        // Test 5: 0 * 0 = 0
        X = 0; Y = 0;
        start_pulse();
        wait(valid == 1);
        #10;
        $display("Test 5: %d * %d = %d (expected %d)", X, Y, Z, X*Y);

        $finish;
    end

    // Task to pulse start for one clock cycle
    task start_pulse;
    begin
        @(negedge clk);
        start = 1;
        @(negedge clk);
        start = 0;
    end
    endtask

endmodule

Booth_Multiplier/booth_multiplier_fsm.vcd
$date
	Sat Aug  9 12:36:00 2025
$end
$version
	Icarus Verilog
$end
$timescale
	1ps
$end
$scope module booth_multiplier_fsm_tb $end
$var wire 1 ! valid $end
$var wire 8 " Z [7:0] $end
$var reg 4 # X [3:0] $end
$var reg 4 $ Y [3:0] $end
$var reg 1 % clk $end
$var reg 1 & rst $end
$var reg 1 ' start $end
$scope module uut $end
$var wire 4 ( X [3:0] $end
$var wire 4 ) Y [3:0] $end
$var wire 1 % clk $end
$var wire 1 & rst $end
$var wire 1 ' start $end
$var parameter 1 * IDLE $end
$var parameter 1 + START $end
$var reg 8 , Z [7:0] $end
$var reg 8 - Z_temp [7:0] $end
$var reg 2 . count [1:0] $end
$var reg 8 / next_Z [7:0] $end
$var reg 2 0 next_count [1:0] $end
$var reg 1 1 next_state $end
$var reg 2 2 next_temp [1:0] $end
$var reg 1 3 next_valid $end
$var reg 1 4 pres_state $end
$var reg 2 5 temp [1:0] $end
$var reg 1 ! valid $end
$upscope $end
$scope task start_pulse $end
$upscope $end
$upscope $end
$enddefinitions $end
$comment Show the parameter values. $end
$dumpall
1+
0*
$end
#0
$dumpvars
b0 5
04
03
b0 2
01
b0 0
b0 /
b0 .
bx -
b0 ,
b0 )
b0 (
0'
0&
0%
b0 $
b0 #
b0 "
0!
$end
#5000
1%
#10000
0%
#15000
1%
1&
#20000
0%
#25000
1%
b11 $
b11 )
b100 #
b100 (
#30000
b100 /
11
1'
0%
#35000
b10 /
b1 0
b100 -
14
b100 "
b100 ,
1%
#40000
0'
0%
#45000
b1 /
b10 0
b10 2
b10 -
b1 .
b10 "
b10 ,
1%
#50000
0%
#55000
b11101000 /
b11 0
b1 2
b11010001 -
b10 .
b10 5
b1 "
b1 ,
1%
#60000
0%
#65000
01
13
b1100 /
b0 0
bx0 2
b11000 -
b11 .
b1 5
b11101000 "
b11101000 ,
1%
#70000
0%
#75000
b0 /
b0 2
03
b0 .
bx0 5
04
1!
b1100 "
b1100 ,
1%
#80000
0%
#85000
b0 5
0!
b0 "
b0 ,
1%
b10 $
b10 )
b1011 #
b1011 (
#90000
b1011 /
b10 2
11
1'
0%
#95000
b11110101 /
b1 0
b11 2
b11101011 -
b10 5
14
b1011 "
b1011 ,
1%
#100000
0'
0%
#105000
b11111010 /
b10 0
b1 2
b11110101 -
b1 .
b11 5
b11110101 "
b11110101 ,
1%
#110000
0%
#115000
b1101 /
b11 0
b10 2
b11010 -
b10 .
b1 5
b11111010 "
b11111010 ,
1%
#120000
0%
#125000
01
13
b11110110 /
b0 0
bx1 2
b11101101 -
b11 .
b10 5
b1101 "
b1101 ,
1%
#130000
0%
#135000
b0 /
b0 2
03
b0 .
bx1 5
04
1!
b11110110 "
b11110110 ,
1%
#140000
0%
#145000
b0 5
0!
b0 "
b0 ,
1%
b1101 $
b1101 )
b1101 #
b1101 (
#150000
b1101 /
b10 2
11
1'
0%
#155000
b11110 /
b1 0
b1 2
b111101 -
b10 5
14
b1101 "
b1101 ,
1%
#160000
0'
0%
#165000
b11110111 /
b10 0
b10 2
b11101110 -
b1 .
b1 5
b11110 "
b11110 ,
1%
#170000
0%
#175000
b10011 /
b11 0
b11 2
b100111 -
b10 .
b10 5
b11110111 "
b11110111 ,
1%
#180000
0%
#185000
01
13
b1001 /
b0 0
bx1 2
b10011 -
b11 .
b11 5
b10011 "
b10011 ,
1%
#190000
0%
#195000
b0 /
b0 2
03
b0 .
bx1 5
04
1!
b1001 "
b1001 ,
1%
#200000
0%
#205000
b0 5
0!
b0 "
b0 ,
1%
b1100 $
b1100 )
b111 #
b111 (
#210000
b111 /
b10 2
11
1'
0%
#215000
b100011 /
b1 0
b11 2
b1000111 -
b10 5
14
b111 "
b111 ,
1%
#220000
0'
0%
#225000
b10001 /
b10 0
b100011 -
b1 .
b11 5
b100011 "
b100011 ,
1%
#230000
0%
#235000
b1000 /
b11 0
b1 2
b10001 -
b10 .
b10001 "
b10001 ,
1%
#240000
0%
#245000
01
13
b11100100 /
b0 0
bx0 2
b11001000 -
b11 .
b1 5
b1000 "
b1000 ,
1%
#250000
0%
#255000
b0 /
b0 2
03
b0 .
bx0 5
04
1!
b11100100 "
b11100100 ,
1%
#260000
0%
#265000
b0 5
0!
b0 "
b0 ,
1%
b0 $
b0 )
b0 #
b0 (
#270000
11
1'
0%
#275000
b1 0
b0 -
14
1%
#280000
0'
0%
#285000
b10 0
b1 .
1%
#290000
0%
#295000
b11 0
b10 .
1%
#300000
0%
#305000
01
13
b0 0
bx0 2
b11 .
1%
#310000
0%
#315000
b0 2
03
b0 .
bx0 5
04
1!
1%
#320000
0%
#325000
b0 5
0!
1%
