RAM_8x4/ram_8x4.v
// 8x4 RAM (Read-Write Memory)

module ram_8x4 (
    input wire clk,
    input wire en,               // Write Enable: 1 = Write, 0 = Read
    input wire [2:0] addr,       // 3-bit Address (0 to 7)
    input wire [3:0] data_in,    // 4-bit Data Input
    output reg [3:0] data_out    // 4-bit Data Output
);

    reg [3:0] memory [7:0]; // 8 words of 4 bits

    always @(posedge clk) begin
        if (en) begin
            memory[addr] <= data_in;    // Write operation
        end else begin
            data_out <= memory[addr];   // Read operation
        end
    end

endmodule

RAM_8x4/ram_8x4_tb.v
// Testbench for 8x4 RAM
`timescale 1ns/1ps

module ram_8x4_tb;

    reg clk;
    reg en;
    reg [2:0] addr;
    reg [3:0] data_in;
    wire [3:0] data_out;

    // Instantiate DUT
    ram_8x4 uut (
        .clk(clk),
        .en(en),
        .addr(addr),
        .data_in(data_in),
        .data_out(data_out)
    );

    // Clock generation
    always #5 clk = ~clk;

    initial begin
        $dumpfile("ram_8x4.vcd");
        $dumpvars(0, ram_8x4_tb);

        clk = 0;

        // Write data
        en = 1;
        addr = 3'b000; data_in = 4'b0001; #10;
        addr = 3'b001; data_in = 4'b0010; #10;
        addr = 3'b010; data_in = 4'b0011; #10;
        addr = 3'b011; data_in = 4'b0100; #10;

        // Read data
        en = 0;
        addr = 3'b000; #10;
        addr = 3'b001; #10;
        addr = 3'b010; #10;
        addr = 3'b011; #10;

        $finish;
    end

endmodule

RAM_8x4/ram_8x4.vcd
$date
	Fri Aug  8 15:48:41 2025
$end
$version
	Icarus Verilog
$end
$timescale
	1ps
$end
$scope module ram_8x4_tb $end
$var wire 4 ! data_out [3:0] $end
$var reg 3 " addr [2:0] $end
$var reg 1 # clk $end
$var reg 4 $ data_in [3:0] $end
$var reg 1 % en $end
$scope module uut $end
$var wire 3 & addr [2:0] $end
$var wire 1 # clk $end
$var wire 4 ' data_in [3:0] $end
$var wire 1 % en $end
$var reg 4 ( data_out [3:0] $end
$upscope $end
$upscope $end
$enddefinitions $end
$comment Show the parameter values. $end
$dumpall
$end
#0
$dumpvars
bx (
b1 '
b0 &
1%
b1 $
0#
b0 "
bx !
$end
#5000
1#
#10000
0#
b10 $
b10 '
b1 "
b1 &
#15000
1#
#20000
0#
b11 $
b11 '
b10 "
b10 &
#25000
1#
#30000
0#
b100 $
b100 '
b11 "
b11 &
#35000
1#
#40000
0#
b0 "
b0 &
0%
#45000
b1 !
b1 (
1#
#50000
0#
b1 "
b1 &
#55000
b10 !
b10 (
1#
#60000
0#
b10 "
b10 &
#65000
b11 !
b11 (
1#
#70000
0#
b11 "
b11 &
#75000
b100 !
b100 (
1#
