Clock_Divider/clock_divider.v
// Clock Divider by 4
module clock_divider (
    input wire clk,
    input wire rst,
    output reg clk_out
);

    reg [1:0] counter;

    initial begin
        counter = 2'b00;
        clk_out = 0;
    end

    always @(posedge clk or posedge rst) begin
        if (rst) begin
            counter <= 2'b00;
            clk_out <= 0;
        end else begin
            counter <= counter + 1;
            if (counter == 2'b11)
                clk_out <= ~clk_out;
        end
    end

endmodule

Clock_Divider/clock_divider_tb.v
`timescale 1ns/1ps

module clock_divider_tb;

    reg clk, rst;
    wire clk_out;

    clock_divider uut (
        .clk(clk),
        .rst(rst),
        .clk_out(clk_out)
    );

    // Clock generation: 10ns period
    always #5 clk = ~clk;

    initial begin
        $dumpfile("clock_divider.vcd");
        $dumpvars(0, clock_divider_tb);

        clk = 0;
        rst = 1; #15;
        rst = 0;

        #200;
        $finish;
    end

endmodule

Clock_Divider/clock_divider.vcd
$date
	Thu Aug  7 23:16:40 2025
$end
$version
	Icarus Verilog
$end
$timescale
	1ps
$end
$scope module clock_divider_tb $end
$var wire 1 ! clk_out $end
$var reg 1 " clk $end
$var reg 1 # rst $end
$scope module uut $end
$var wire 1 " clk $end
$var wire 1 # rst $end
$var reg 1 ! clk_out $end
$var reg 2 $ counter [1:0] $end
$upscope $end
$upscope $end
$enddefinitions $end
$comment Show the parameter values. $end
$dumpall
$end
#0
$dumpvars
b0 $
1#
0"
0!
$end
#5000
1"
#10000
0"
#15000
b1 $
1"
0#
#20000
0"
#25000
b10 $
1"
#30000
0"
#35000
b11 $
1"
#40000
0"
#45000
1!
b0 $
1"
#50000
0"
#55000
b1 $
1"
#60000
0"
#65000
b10 $
1"
#70000
0"
#75000
b11 $
1"
#80000
0"
#85000
0!
b0 $
1"
#90000
0"
#95000
b1 $
1"
#100000
0"
#105000
b10 $
1"
#110000
0"
#115000
b11 $
1"
#120000
0"
#125000
1!
b0 $
1"
#130000
0"
#135000
b1 $
1"
#140000
0"
#145000
b10 $
1"
#150000
0"
#155000
b11 $
1"
#160000
0"
#165000
0!
b0 $
1"
#170000
0"
#175000
b1 $
1"
#180000
0"
#185000
b10 $
1"
#190000
0"
#195000
b11 $
1"
#200000
0"
#205000
1!
b0 $
1"
#210000
0"
#215000
b1 $
1"
